python_chargepoint/__init__.py
python_chargepoint/__main__.py
python_chargepoint/client.py
python_chargepoint/constants.py
python_chargepoint/exceptions.py
python_chargepoint/global_config.py
python_chargepoint/session.py
python_chargepoint/types.py
python_chargepoint-1.10.0.dist-info/LICENSE
python_chargepoint-1.10.0.dist-info/METADATA
python_chargepoint-1.10.0.dist-info/WHEEL
python_chargepoint-1.10.0.dist-info/RECORD
