Metadata-Version: 2.3
Name: python-chargepoint
Version: 1.10.0
Summary: A simple, Pythonic wrapper for the ChargePoint API.
License: MIT
Author: Marc Billow
Author-email: mbillow@users.noreply.github.compoetry
Requires-Python: >=3.9,<4.0
Classifier: License :: OSI Approved :: MIT License
Classifier: Programming Language :: Python :: 3
Classifier: Programming Language :: Python :: 3.9
Classifier: Programming Language :: Python :: 3.10
Classifier: Programming Language :: Python :: 3.11
Classifier: Programming Language :: Python :: 3.12
Classifier: Programming Language :: Python :: 3.13
Requires-Dist: requests (>=2.32.3,<3.0.0)
